criapi/__init__.py
criapi/__main__.py
criapi-1.0.5.dist-info/LICENSE
criapi-1.0.5.dist-info/METADATA
criapi-1.0.5.dist-info/WHEEL
criapi-1.0.5.dist-info/top_level.txt
criapi-1.0.5.dist-info/RECORD
