Metadata-Version: 2.1
Name: criapi
Version: 1.0.5
Summary: An API to get cricket scores,scorecards and commentary in python.
Home-page: https://github.com/sAksham-Ar/criapi
Author: Saksham Arya
Author-email: aryasaksham@gmail.com
License: GPLv3
Platform: UNKNOWN
Classifier: License :: OSI Approved :: GNU General Public License v3 (GPLv3)
Classifier: Programming Language :: Python :: 3
Classifier: Programming Language :: Python :: 3.8
Requires-Dist: requests
Requires-Dist: bs4
